<?xml version="1.0" encoding="UTF-8"?>
<items>
  <item name="dungeon silver key">
    <type class="key" subclass="silver" tileid="-1"/>
    <description>You see a silver dungeon key. Use it only if you are brave.</description>
    <implementation class-name="games.stendhal.server.entity.item.Item"/>    <attributes>
    </attributes>
    <weight value="1.0"/>
    <value value="1"/>
    <equipable>
      <slot name="bag"/>
      <slot name="keyring"/>
    </equipable>
  </item>

  <item name="lich gold key">
    <type class="key" subclass="gold" tileid="-1"/>
    <description>You see a golden lich key. It will open the door to terrible things.</description>
    <implementation class-name="games.stendhal.server.entity.item.Item"/>    <attributes>
    </attributes>
    <weight value="1.0"/>
    <value value="1"/>
    <equipable>
      <slot name="bag"/>
      <slot name="keyring"/>
    </equipable>
  </item>

  <item name="minotaur key">
    <type class="key" subclass="bronze" tileid="-1"/>
    <description>You see a fancy bronze key. It smells faintly of minotaur, perhaps one dropped it?</description>
    <implementation class-name="games.stendhal.server.entity.item.Item"/>    <attributes>
    </attributes>
    <weight value="1.0"/>
    <value value="1"/>
    <equipable>
      <slot name="bag"/>
      <slot name="keyring"/>
    </equipable>
  </item>

  <item name="nalwor bank key">
    <type class="key" subclass="nalwor" tileid="-1"/>
    <description>You see a key to the customer room of Nalwor Bank.</description>
    <implementation class-name="games.stendhal.server.entity.item.Item"/>    <attributes>
    </attributes>
    <weight value="1.0"/>
    <value value="1"/>
    <equipable>
      <slot name="bag"/>
      <slot name="keyring"/>
    </equipable>
  </item>

  <item name="kotoch prison key">
    <type class="key" subclass="copper" tileid="-1"/>
    <description>You see an ancient copper key, enscribed with something in Orcish.</description>
    <implementation class-name="games.stendhal.server.entity.item.Item"/>    <attributes>
    </attributes>
    <weight value="1.0"/>
    <value value="1"/>
    <equipable>
      <slot name="bag"/>
      <slot name="keyring"/>
    </equipable>
  </item>

  <item name="kanmararn prison key">
    <type class="key" subclass="blue" tileid="-1"/>
    <description>You see a key which matches the locks in the Kanmararn prison.</description>
    <implementation class-name="games.stendhal.server.entity.item.Item"/>    <attributes>
    </attributes>
    <weight value="1.0"/>
    <value value="1"/>
    <equipable>
      <slot name="bag"/>
      <slot name="keyring"/>
    </equipable>
  </item>

  <item name="sedah gate key">
    <type class="key" subclass="square" tileid="-1"/>
    <description>You see a key for the gate to the imperial city of Sedah.</description>
    <implementation class-name="games.stendhal.server.entity.item.Item"/>    <attributes>
    </attributes>
    <weight value="1.0"/>
    <value value="1"/>
    <equipable>
      <slot name="bag"/>
      <slot name="keyring"/>
    </equipable>
  </item>

 <item name="private key 1">
    <type class="key" subclass="purple" tileid="-1"/>
    <description>You see a private key to House 1 in Kalavan City.</description>
    <implementation class-name="games.stendhal.server.entity.item.Item"/>    <attributes>
    </attributes>
    <weight value="1.0"/>
    <value value="1"/>
    <equipable>
      <slot name="bag"/>
      <slot name="keyring"/>
    </equipable>
  </item>
 <item name="private key 2">
    <type class="key" subclass="turquoise" tileid="-1"/>
    <description>You see a private key to House 2 in Kalavan City.</description>
    <implementation class-name="games.stendhal.server.entity.item.Item"/>    <attributes>
    </attributes>
    <weight value="1.0"/>
    <value value="1"/>
    <equipable>
      <slot name="bag"/>
      <slot name="keyring"/>
    </equipable>
  </item>
 <item name="private key 3">
    <type class="key" subclass="yellow" tileid="-1"/>
    <description>You see a private key to House 3 in Kalavan City.</description>
    <implementation class-name="games.stendhal.server.entity.item.Item"/>    <attributes>
    </attributes>
    <weight value="1.0"/>
    <value value="1"/>
    <equipable>
      <slot name="bag"/>
      <slot name="keyring"/>
    </equipable>
  </item>
 <item name="private key 4">
    <type class="key" subclass="lime" tileid="-1"/>
    <description>You see a private key to House 4 in Kalavan City.</description>
    <implementation class-name="games.stendhal.server.entity.item.Item"/>    <attributes>
    </attributes>
    <weight value="1.0"/>
    <value value="1"/>
    <equipable>
      <slot name="bag"/>
      <slot name="keyring"/>
    </equipable>
  </item>
 <item name="private key 5">
    <type class="key" subclass="pink" tileid="-1"/>
    <description>You see a private key to House 5 in Kalavan City.</description>
    <implementation class-name="games.stendhal.server.entity.item.Item"/>    <attributes>
    </attributes>
    <weight value="1.0"/>
    <value value="1"/>
    <equipable>
      <slot name="bag"/>
      <slot name="keyring"/>
    </equipable>
  </item>
 <item name="private key 6">
    <type class="key" subclass="red" tileid="-1"/>
    <description>You see a private key to House 6 in Kalavan City.</description>
    <implementation class-name="games.stendhal.server.entity.item.Item"/>    <attributes>
    </attributes>
    <weight value="1.0"/>
    <value value="1"/>
    <equipable>
      <slot name="bag"/>
      <slot name="keyring"/>
    </equipable>
  </item>
 <item name="private key 7">
    <type class="key" subclass="orange" tileid="-1"/>
    <description>You see a private key to House 7 in Kalavan City.</description>
    <implementation class-name="games.stendhal.server.entity.item.Item"/>    <attributes>
    </attributes>
    <weight value="1.0"/>
    <value value="1"/>
    <equipable>
      <slot name="bag"/>
      <slot name="keyring"/>
    </equipable>
  </item>
 <item name="private key 8">
    <type class="key" subclass="navy" tileid="-1"/>
    <description>You see a private key to House 8 in Kalavan City.</description>
    <implementation class-name="games.stendhal.server.entity.item.Item"/>    <attributes>
    </attributes>
    <weight value="1.0"/>
    <value value="1"/>
    <equipable>
      <slot name="bag"/>
      <slot name="keyring"/>
    </equipable>
  </item>
 <item name="private key 9">
    <type class="key" subclass="purple" tileid="-1"/>
    <description>You see a private key to House 9 in Kalavan City.</description>
    <implementation class-name="games.stendhal.server.entity.item.Item"/>    <attributes>
    </attributes>
    <weight value="1.0"/>
    <value value="1"/>
    <equipable>
      <slot name="bag"/>
      <slot name="keyring"/>
    </equipable>
  </item>
 <item name="private key 10">
    <type class="key" subclass="turquoise" tileid="-1"/>
    <description>You see a private key to House 10 in Kalavan City.</description>
    <implementation class-name="games.stendhal.server.entity.item.Item"/>    <attributes>
    </attributes>
    <weight value="1.0"/>
    <value value="1"/>
    <equipable>
      <slot name="bag"/>
      <slot name="keyring"/>
    </equipable>
  </item>
 <item name="private key 11">
    <type class="key" subclass="lime" tileid="-1"/>
    <description>You see a private key to House 11 in Kalavan City.</description>
    <implementation class-name="games.stendhal.server.entity.item.Item"/>    <attributes>
    </attributes>
    <weight value="1.0"/>
    <value value="1"/>
    <equipable>
      <slot name="bag"/>
      <slot name="keyring"/>
    </equipable>
  </item>
 <item name="private key 12">
    <type class="key" subclass="yellow" tileid="-1"/>
    <description>You see a private key to House 12 in Kalavan City.</description>
    <implementation class-name="games.stendhal.server.entity.item.Item"/>    <attributes>
    </attributes>
    <weight value="1.0"/>
    <value value="1"/>
    <equipable>
      <slot name="bag"/>
      <slot name="keyring"/>
    </equipable>
  </item>
 <item name="private key 13">
    <type class="key" subclass="navy" tileid="-1"/>
    <description>You see a private key to House 13 in Kalavan City.</description>
    <implementation class-name="games.stendhal.server.entity.item.Item"/>    <attributes>
    </attributes>
    <weight value="1.0"/>
    <value value="1"/>
    <equipable>
      <slot name="bag"/>
      <slot name="keyring"/>
    </equipable>
  </item>
 <item name="private key 14">
    <type class="key" subclass="pink" tileid="-1"/>
    <description>You see a private key to House 14 in Kalavan City.</description>
    <implementation class-name="games.stendhal.server.entity.item.Item"/>    <attributes>
    </attributes>
    <weight value="1.0"/>
    <value value="1"/>
    <equipable>
      <slot name="bag"/>
      <slot name="keyring"/>
    </equipable>
  </item>
 <item name="private key 15">
    <type class="key" subclass="orange" tileid="-1"/>
    <description>You see a private key to House 15 in Kalavan City.</description>
    <implementation class-name="games.stendhal.server.entity.item.Item"/>    <attributes>
    </attributes>
    <weight value="1.0"/>
    <value value="1"/>
    <equipable>
      <slot name="bag"/>
      <slot name="keyring"/>
    </equipable>
  </item>
 <item name="private key 16">
    <type class="key" subclass="red" tileid="-1"/>
    <description>You see a private key to House 16 in Kalavan City.</description>
    <implementation class-name="games.stendhal.server.entity.item.Item"/>    <attributes>
    </attributes>
    <weight value="1.0"/>
    <value value="1"/>
    <equipable>
      <slot name="bag"/>
      <slot name="keyring"/>
    </equipable>
  </item>
 <item name="private key 17">
    <type class="key" subclass="purple" tileid="-1"/>
    <description>You see a private key to House 17 in Kalavan City.</description>
    <implementation class-name="games.stendhal.server.entity.item.Item"/>    <attributes>
    </attributes>
    <weight value="1.0"/>
    <value value="1"/>
    <equipable>
      <slot name="bag"/>
      <slot name="keyring"/>
    </equipable>
  </item>
 <item name="private key 18">
    <type class="key" subclass="turquoise" tileid="-1"/>
    <description>You see a private key to House 18 in Kalavan City.</description>
    <implementation class-name="games.stendhal.server.entity.item.Item"/>    <attributes>
    </attributes>
    <weight value="1.0"/>
    <value value="1"/>
    <equipable>
      <slot name="bag"/>
      <slot name="keyring"/>
    </equipable>
  </item>
 <item name="private key 19">
    <type class="key" subclass="yellow" tileid="-1"/>
    <description>You see a private key to House 19 in Kalavan City.</description>
    <implementation class-name="games.stendhal.server.entity.item.Item"/>    <attributes>
    </attributes>
    <weight value="1.0"/>
    <value value="1"/>
    <equipable>
      <slot name="bag"/>
      <slot name="keyring"/>
    </equipable>
  </item>
 <item name="private key 20">
    <type class="key" subclass="orange" tileid="-1"/>
    <description>You see a private key to House 20 in Kalavan City.</description>
    <implementation class-name="games.stendhal.server.entity.item.Item"/>    <attributes>
    </attributes>
    <weight value="1.0"/>
    <value value="1"/>
    <equipable>
      <slot name="bag"/>
      <slot name="keyring"/>
    </equipable>
  </item>
 <item name="private key 21">
    <type class="key" subclass="lime" tileid="-1"/>
    <description>You see a private key to House 21 in Kalavan City.</description>
    <implementation class-name="games.stendhal.server.entity.item.Item"/>    <attributes>
    </attributes>
    <weight value="1.0"/>
    <value value="1"/>
    <equipable>
      <slot name="bag"/>
      <slot name="keyring"/>
    </equipable>
  </item>
 <item name="private key 22">
    <type class="key" subclass="pink" tileid="-1"/>
    <description>You see a private key to House 22 in Kalavan City.</description>
    <implementation class-name="games.stendhal.server.entity.item.Item"/>    <attributes>
    </attributes>
    <weight value="1.0"/>
    <value value="1"/>
    <equipable>
      <slot name="bag"/>
      <slot name="keyring"/>
    </equipable>
  </item>
 <item name="private key 23">
    <type class="key" subclass="navy" tileid="-1"/>
    <description>You see a private key to House 23 in Kalavan City.</description>
    <implementation class-name="games.stendhal.server.entity.item.Item"/>    <attributes>
    </attributes>
    <weight value="1.0"/>
    <value value="1"/>
    <equipable>
      <slot name="bag"/>
      <slot name="keyring"/>
    </equipable>
  </item>
 <item name="private key 24">
    <type class="key" subclass="red" tileid="-1"/>
    <description>You see a private key to House 24 in Kalavan City.</description>
    <implementation class-name="games.stendhal.server.entity.item.Item"/>    <attributes>
    </attributes>
    <weight value="1.0"/>
    <value value="1"/>
    <equipable>
      <slot name="bag"/>
      <slot name="keyring"/>
    </equipable>
  </item>
 <item name="private key 25">
    <type class="key" subclass="pink" tileid="-1"/>
    <description>You see a private key to House 25 in Kalavan City.</description>
    <implementation class-name="games.stendhal.server.entity.item.Item"/>    <attributes>
    </attributes>
    <weight value="1.0"/>
    <value value="1"/>
    <equipable>
      <slot name="bag"/>
      <slot name="keyring"/>
    </equipable>
  </item>

 <item name="private key 44">
    <type class="key" subclass="navy" tileid="-1"/>
    <description>You see a private key to House 44 in Kirdneh City.</description>
    <implementation class-name="games.stendhal.server.entity.item.Item"/>    <attributes>
    </attributes>
    <weight value="1.0"/>
    <value value="1"/>
    <equipable>
      <slot name="bag"/>
      <slot name="keyring"/>
    </equipable>
  </item>


 <item name="private key 50">
    <type class="key" subclass="yellow" tileid="-1"/>
    <description>You see a private key to House 50 in Ados City N.</description>
    <implementation class-name="games.stendhal.server.entity.item.Item"/>    <attributes>
    </attributes>
    <weight value="1.0"/>
    <value value="1"/>
    <equipable>
      <slot name="bag"/>
      <slot name="keyring"/>
    </equipable>
  </item>
 <item name="private key 51">
    <type class="key" subclass="red" tileid="-1"/>
    <description>You see a private key to House 51 in Ados City N.</description>
    <implementation class-name="games.stendhal.server.entity.item.Item"/>    <attributes>
    </attributes>
    <weight value="1.0"/>
    <value value="1"/>
    <equipable>
      <slot name="bag"/>
      <slot name="keyring"/>
    </equipable>
  </item>
 <item name="private key 52">
    <type class="key" subclass="orange" tileid="-1"/>
    <description>You see a private key to House 52 in Ados City N.</description>
    <implementation class-name="games.stendhal.server.entity.item.Item"/>    <attributes>
    </attributes>
    <weight value="1.0"/>
    <value value="1"/>
    <equipable>
      <slot name="bag"/>
      <slot name="keyring"/>
    </equipable>
  </item>
 <item name="private key 53">
    <type class="key" subclass="purple" tileid="-1"/>
    <description>You see a private key to House 53 in Ados City N.</description>
    <implementation class-name="games.stendhal.server.entity.item.Item"/>    <attributes>
    </attributes>
    <weight value="1.0"/>
    <value value="1"/>
    <equipable>
      <slot name="bag"/>
      <slot name="keyring"/>
    </equipable>
  </item>
 <item name="private key 54">
    <type class="key" subclass="lime" tileid="-1"/>
    <description>You see a private key to House 54 in Ados City N.</description>
    <implementation class-name="games.stendhal.server.entity.item.Item"/>    <attributes>
    </attributes>
    <weight value="1.0"/>
    <value value="1"/>
    <equipable>
      <slot name="bag"/>
      <slot name="keyring"/>
    </equipable>
  </item>
 <item name="private key 55">
    <type class="key" subclass="pink" tileid="-1"/>
    <description>You see a private key to House 55 in Ados City N.</description>
    <implementation class-name="games.stendhal.server.entity.item.Item"/>    <attributes>
    </attributes>
    <weight value="1.0"/>
    <value value="1"/>
    <equipable>
      <slot name="bag"/>
      <slot name="keyring"/>
    </equipable>
  </item>
 <item name="private key 56">
    <type class="key" subclass="red" tileid="-1"/>
    <description>You see a private key to House 56 in Ados City N.</description>
    <implementation class-name="games.stendhal.server.entity.item.Item"/>    <attributes>
    </attributes>
    <weight value="1.0"/>
    <value value="1"/>
    <equipable>
      <slot name="bag"/>
      <slot name="keyring"/>
    </equipable>
  </item>
 <item name="private key 57">
    <type class="key" subclass="orange" tileid="-1"/>
    <description>You see a private key to House 57 in Ados City N.</description>
    <implementation class-name="games.stendhal.server.entity.item.Item"/>    <attributes>
    </attributes>
    <weight value="1.0"/>
    <value value="1"/>
    <equipable>
      <slot name="bag"/>
      <slot name="keyring"/>
    </equipable>
  </item>
 <item name="private key 58">
    <type class="key" subclass="navy" tileid="-1"/>
    <description>You see a private key to House 58 in Ados City N.</description>
    <implementation class-name="games.stendhal.server.entity.item.Item"/>    <attributes>
    </attributes>
    <weight value="1.0"/>
    <value value="1"/>
    <equipable>
      <slot name="bag"/>
      <slot name="keyring"/>
    </equipable>
 </item>
 <item name="private key 59">
    <type class="key" subclass="yellow" tileid="-1"/>
    <description>You see a private key to House 59 in Ados City N.</description>
    <implementation class-name="games.stendhal.server.entity.item.Item"/>    <attributes>
    </attributes>
    <weight value="1.0"/>
    <value value="1"/>
    <equipable>
      <slot name="bag"/>
      <slot name="keyring"/>
    </equipable>
  </item>
 <item name="private key 60">
    <type class="key" subclass="yellow" tileid="-1"/>
    <description>You see a private key to House 60 in Ados City N.</description>
    <implementation class-name="games.stendhal.server.entity.item.Item"/>    <attributes>
    </attributes>
    <weight value="1.0"/>
    <value value="1"/>
    <equipable>
      <slot name="bag"/>
      <slot name="keyring"/>
    </equipable>
  </item>
 <item name="private key 61">
    <type class="key" subclass="yellow" tileid="-1"/>
    <description>You see a private key to House 61 in Ados City N.</description>
    <implementation class-name="games.stendhal.server.entity.item.Item"/>    <attributes>
    </attributes>
    <weight value="1.0"/>
    <value value="1"/>
    <equipable>
      <slot name="bag"/>
      <slot name="keyring"/>
    </equipable>
  </item>
 <item name="private key 62">
    <type class="key" subclass="yellow" tileid="-1"/>
    <description>You see a private key to House 62 in Ados City N.</description>
    <implementation class-name="games.stendhal.server.entity.item.Item"/>    <attributes>
    </attributes>
    <weight value="1.0"/>
    <value value="1"/>
    <equipable>
      <slot name="bag"/>
      <slot name="keyring"/>
    </equipable>
  </item>
 <item name="private key 63">
    <type class="key" subclass="yellow" tileid="-1"/>
    <description>You see a private key to House 63 in Ados City.</description>
    <implementation class-name="games.stendhal.server.entity.item.Item"/>    <attributes>
    </attributes>
    <weight value="1.0"/>
    <value value="1"/>
    <equipable>
      <slot name="bag"/>
      <slot name="keyring"/>
    </equipable>
  </item>
 <item name="private key 64">
    <type class="key" subclass="lime" tileid="-1"/>
    <description>You see a private key to House 64 in Ados City.</description>
    <implementation class-name="games.stendhal.server.entity.item.Item"/>    <attributes>
    </attributes>
    <weight value="1.0"/>
    <value value="1"/>
    <equipable>
      <slot name="bag"/>
      <slot name="keyring"/>
    </equipable>
  </item>
 <item name="private key 65">
    <type class="key" subclass="pink" tileid="-1"/>
    <description>You see a private key to House 65 in Ados City.</description>
    <implementation class-name="games.stendhal.server.entity.item.Item"/>    <attributes>
    </attributes>
    <weight value="1.0"/>
    <value value="1"/>
    <equipable>
      <slot name="bag"/>
      <slot name="keyring"/>
    </equipable>
  </item>
 <item name="private key 66">
    <type class="key" subclass="red" tileid="-1"/>
    <description>You see a private key to House 66 in Ados City.</description>
    <implementation class-name="games.stendhal.server.entity.item.Item"/>    <attributes>
    </attributes>
    <weight value="1.0"/>
    <value value="1"/>
    <equipable>
      <slot name="bag"/>
      <slot name="keyring"/>
    </equipable>
  </item>
 <item name="private key 67">
    <type class="key" subclass="orange" tileid="-1"/>
    <description>You see a private key to House 67 in Ados City.</description>
    <implementation class-name="games.stendhal.server.entity.item.Item"/>    <attributes>
    </attributes>
    <weight value="1.0"/>
    <value value="1"/>
    <equipable>
      <slot name="bag"/>
      <slot name="keyring"/>
    </equipable>
  </item>
 <item name="private key 68">
    <type class="key" subclass="navy" tileid="-1"/>
    <description>You see a private key to House 68 in Ados City.</description>
    <implementation class-name="games.stendhal.server.entity.item.Item"/>    <attributes>
    </attributes>
    <weight value="1.0"/>
    <value value="1"/>
    <equipable>
      <slot name="bag"/>
      <slot name="keyring"/>
    </equipable>
  </item>

  <item name="fado hotel key 001">
    <type class="key" subclass="hotel" tileid="-1"/>
    <description>You see a key to room #001 in the Fado Hotel.</description>
    <implementation class-name="games.stendhal.server.entity.item.Item"/>    <attributes>
    </attributes>
    <weight value="1.0"/>
    <value value="1"/>
    <equipable>
      <slot name="bag"/>
      <slot name="keyring"/>
    </equipable>
  </item>

  <item name="fado hotel key 002">
    <type class="key" subclass="hotel" tileid="-1"/>
    <description>You see a key to room #002 in the Fado Hotel.</description>
    <implementation class-name="games.stendhal.server.entity.item.Item"/>    <attributes>
    </attributes>
    <weight value="1.0"/>
    <value value="1"/>
    <equipable>
      <slot name="bag"/>
      <slot name="keyring"/>
    </equipable>
  </item>

  <item name="fado hotel key 003">
    <type class="key" subclass="hotel" tileid="-1"/>
    <description>You see a key to room #003 in the Fado Hotel.</description>
    <implementation class-name="games.stendhal.server.entity.item.Item"/>    <attributes>
    </attributes>
    <weight value="1.0"/>
    <value value="1"/>
    <equipable>
      <slot name="bag"/>
      <slot name="keyring"/>
    </equipable>
  </item>

  <item name="fado hotel key 004">
    <type class="key" subclass="hotel" tileid="-1"/>
    <description>You see a key to room #004 in the Fado Hotel.</description>
    <implementation class-name="games.stendhal.server.entity.item.Item"/>    <attributes>
    </attributes>
    <weight value="1.0"/>
    <value value="1"/>
    <equipable>
      <slot name="bag"/>
      <slot name="keyring"/>
    </equipable>
  </item>

  <item name="fado hotel key 005">
    <type class="key" subclass="hotel" tileid="-1"/>
    <description>You see a key to room #005 in the Fado Hotel.</description>
    <implementation class-name="games.stendhal.server.entity.item.Item"/>    <attributes>
    </attributes>
    <weight value="1.0"/>
    <value value="1"/>
    <equipable>
      <slot name="bag"/>
      <slot name="keyring"/>
    </equipable>
  </item>

  <item name="fado hotel key 006">
    <type class="key" subclass="hotel" tileid="-1"/>
    <description>You see a key to room #006 in the Fado Hotel.</description>
    <implementation class-name="games.stendhal.server.entity.item.Item"/>    <attributes>
    </attributes>
    <weight value="1.0"/>
    <value value="1"/>
    <equipable>
      <slot name="bag"/>
      <slot name="keyring"/>
    </equipable>
  </item>

  <item name="fado hotel key 007">
    <type class="key" subclass="hotel" tileid="-1"/>
    <description>You see a key to room #007 in the Fado Hotel.</description>
    <implementation class-name="games.stendhal.server.entity.item.Item"/>    <attributes>
    </attributes>
    <weight value="1.0"/>
    <value value="1"/>
    <equipable>
      <slot name="bag"/>
      <slot name="keyring"/>
    </equipable>
  </item>

  <item name="fado hotel key 008">
    <type class="key" subclass="hotel" tileid="-1"/>
    <description>You see a key to room #008 in the Fado Hotel.</description>
    <implementation class-name="games.stendhal.server.entity.item.Item"/>    <attributes>
    </attributes>
    <weight value="1.0"/>
    <value value="1"/>
    <equipable>
      <slot name="bag"/>
      <slot name="keyring"/>
    </equipable>
  </item>

  <item name="small key">
    <type class="key" subclass="common" tileid="-1"/>
    <description>You see the key for Zara's row house in Ados.</description>
    <implementation class-name="games.stendhal.server.entity.item.Item"/>    <attributes>
    </attributes>
    <weight value="1.0"/>
    <value value="1"/>
    <equipable>
      <slot name="bag"/>
      <slot name="keyring"/>
    </equipable>
  </item>
</items>